model_config_tests/__init__.py
model_config_tests/_version.py
model_config_tests/exp_test_helper.py
model_config_tests/util.py
model_config_tests/cmds/compare_exp_tests_cmd.py
model_config_tests/cmds/config_tests_cmd.py
model_config_tests/compare_exp_tests/conftest.py
model_config_tests/compare_exp_tests/test_repro.py
model_config_tests/config_tests/conftest.py
model_config_tests/config_tests/test_bit_reproducibility.py
model_config_tests/config_tests/qa/test_access_esm1p5_config.py
model_config_tests/config_tests/qa/test_access_esm1p6_config.py
model_config_tests/config_tests/qa/test_access_om2_config.py
model_config_tests/config_tests/qa/test_access_om3_config.py
model_config_tests/config_tests/qa/test_config.py
model_config_tests/models/__init__.py
model_config_tests/models/accessesm1p5.py
model_config_tests/models/accessesm1p6.py
model_config_tests/models/accessom2.py
model_config_tests/models/accessom3.py
model_config_tests/models/model.py
model_config_tests/models/mom5.py
model_config_tests/models/um7.py
model_config_tests-0.2.3.dist-info/licenses/LICENSE
model_config_tests-0.2.3.dist-info/METADATA
model_config_tests-0.2.3.dist-info/WHEEL
model_config_tests-0.2.3.dist-info/entry_points.txt
model_config_tests-0.2.3.dist-info/top_level.txt
model_config_tests-0.2.3.dist-info/RECORD
