Metadata-Version: 2.4
Name: model_config_tests
Version: 0.2.3
Summary: Test for ACCESS model (payu) configurations
Author: ACCESS-NRI
License: Apache-2.0
Project-URL: Homepage, https://github.com/ACCESS-NRI/model-config-tests/
Project-URL: Issues, https://github.com/ACCESS-NRI/model-config-tests/issues
Classifier: Programming Language :: Python :: 3
Classifier: License :: OSI Approved :: Apache Software License
Classifier: Operating System :: POSIX :: Linux
Requires-Python: >=3.9
License-File: LICENSE
Requires-Dist: f90nml>=0.16
Requires-Dist: requests
Requires-Dist: PyYAML
Requires-Dist: requests
Requires-Dist: pytest>=8.0.1
Requires-Dist: ruamel.yaml>=0.18.5
Requires-Dist: jsonschema>=4.21.1
Requires-Dist: payu>=1.1.3
Requires-Dist: pytest-sugar
Requires-Dist: netCDF4
Provides-Extra: test
Requires-Dist: pytest-cov; extra == "test"
Dynamic: license-file
